{"inkVersion":21,"root":[["^¿Buenas, qué les trae por aquí? ","#","^speaker:Arquitecto ","/#","#","^portrait:npc-neutral ","/#","#","^layout:left","/#","\n","^Venimos del palacio de Villores, un músico nos ha otorgado este sello. ¿Necesita algo? ","#","^speaker:Silvia ","/#","#","^portrait:silvia-neutral ","/#","#","^layout:right","/#","\n","^Gracias a Dios ha venido alguien a ayudar, llevamos unos días intentando remodelar la plaza pero no nos acaba de convencer ningún diseño. Los arquitectos están desesperados y esto hace que tengamos que dar un rodeo muy grande para llegar a la <color=#FF1E35>Iglesia Arciprestal</color>. ","#","^speaker:Arquitecto ","/#","#","^portrait:npc-neutral ","/#","#","^layout:left","/#","\n","^Si quieren ayudarnos, pueden coger el <b>compás</b> del suelo. ","#","^speaker:Arquitecto ","/#","#","^portrait:npc-neutral ","/#","#","^layout:left","/#","\n",["done",{"#f":5,"#n":"g-0"}],null],"done",{"#f":1}],"listDefs":{}}